<?xml version="1.0" encoding="UTF-8" standalone="no" ?>
<Application>

  <Header>
    <Version val="13010"/>
    <WithIsn val="Y"/>
    <_InternalTask val="N"/>
    <IsRoot val="N"/>
    <InIndex val="N"/>
    <UniqueISNConvState val="10"/>
  </Header>

  <ProgramsRepository>
    <Programs>
      <Task MainProgram="N">
        <Header Description="目標マスタ保守" ISN_2="1" LastIsn="1" id="602">
          <Public val="MokMst"/>
          <ExecutionRight comp="-1"/>
          <Resident val="N"/>
          <SQL val="N"/>
          <ReturnValue>
            <ReturnValueAttr/>
            <ParametersAttributes/>
          </ReturnValue>
          <SqlWhereExist val="N"/>
          <TaskType val="O"/>
          <External val="Y"/>
          <Offline val="N"/>
          <FormType val="N"/>
          <DotNetObjectExists val="N"/>
          <LastModified _date="736342" _time="37308" date="2017/01/13" time="10:21:48"/>
        </Header>
        <ItemIsn val="25"/>
        <Resource>
          <DB id="1">
            <DataObject comp="-1" obj="502"/>
            <Access val="W"/>
            <Share val="W"/>
            <Open val="N"/>
            <Cache val="Y"/>
            <IdentifyRowModifications val="84"/>
          </DB>
          <Columns/>
        </Resource>
        <Information>
          <Key>
            <Column val="1"/>
            <Mode val="N"/>
          </Key>
          <DB comp="-1" obj="502"/>
          <Sort>
            <CLS val="A"/>
          </Sort>
          <ForceRecordDelete DEL="N"/>
          <EndTaskCondition val="N"/>
          <EvaluateEndCondition val="B"/>
          <InitialMode val="M"/>
          <Locate Direction="A"/>
          <Range Direction="A"/>
          <VarRange/>
          <TaskProperties>
            <SelectionTable val="N"/>
            <ConfirmUpdate CNFU="N"/>
            <ConfirmCancel val="N"/>
            <ErrorStrategy val="R"/>
            <LockingStrategy val="O"/>
            <CacheStrategy val="T"/>
            <ForceRecordSuffix val="N"/>
            <TransactionMode val="P"/>
            <TransactionBegin val="L"/>
            <PreloadView val="N"/>
            <AllowEmptyDataview val="N"/>
            <KeepCreatedContext val="N"/>
          </TaskProperties>
          <SIDE_WIN>
            <AllowOptions val="Y"/>
            <AllowQuery val="Y"/>
            <AllowModify val="Y"/>
            <AllowCreate val="Y"/>
            <AllowDelete val="Y"/>
            <AllowLocate val="Y"/>
            <AllowRange val="Y"/>
            <AllowIndexChange val="Y"/>
            <AllowSorting val="Y"/>
            <AllowIOFiles val="Y"/>
            <RecordCycle val="Y"/>
            <AllowEvents val="Y"/>
            <AllowIndexOptimization val="N"/>
            <AllowLocationInQuery val="N"/>
            <AllowPrintingData val="N"/>
          </SIDE_WIN>
          <WIN>
            <OpenTaskWindow val="Y"/>
            <CloseTaskWindow val="Y"/>
            <ForegroundWindow val="Y"/>
            <FlipFld val="N"/>
            <RefreshTaskWindow ReturnValue="N"/>
          </WIN>
          <BOX>
            <Direction val="V"/>
          </BOX>
        </Information>
        <TaskLogic>
          <LogicUnit id="2" propagate="78">
            <Level val="R"/>
            <Type val="M"/>
            <_DspTemplate val="0"/>
            <_HeaderPosition val="1"/>
            <Scope val="S"/>
            <EngineDirective val="S"/>
            <ShowMessage val="Y"/>
            <Condition val="89"/>
            <Event>
              <EventType val="S"/>
              <PublicObject comp="-1"/>
            </Event>
            <LogicLines>
              <LogicLine>
                <DATAVIEW_SRC FlowIsn="2" IDX="1" Type="M">
                  <Condition val="N"/>
                  <Modifier val="B"/>
                  <Direction val="C"/>
                </DATAVIEW_SRC>
              </LogicLine>
              <LogicLine>
                <Select FieldID="1" FlowIsn="3" id="1">
                  <Column val="1"/>
                  <Type val="R"/>
                  <IsParameter val="N"/>
                  <_DitIndexForToolkit val="27"/>
                  <DIFF_UPDATE val="T"/>
                  <Condition val="Y"/>
                  <Modifier val="S"/>
                  <Direction val="C"/>
                </Select>
              </LogicLine>
              <LogicLine>
                <Select FieldID="2" FlowIsn="4" id="2">
                  <Column val="2"/>
                  <Type val="R"/>
                  <IsParameter val="N"/>
                  <_DitIndexForToolkit val="28"/>
                  <DIFF_UPDATE val="T"/>
                  <Condition val="Y"/>
                  <Modifier val="S"/>
                  <Direction val="C"/>
                </Select>
              </LogicLine>
              <LogicLine>
                <Select FieldID="3" FlowIsn="5" id="3">
                  <Column val="47"/>
                  <Type val="R"/>
                  <IsParameter val="N"/>
                  <_DitIndexForToolkit val="29"/>
                  <DIFF_UPDATE val="T"/>
                  <Condition val="Y"/>
                  <Modifier val="S"/>
                  <Direction val="C"/>
                </Select>
              </LogicLine>
              <LogicLine>
                <Select FieldID="4" FlowIsn="6" id="4">
                  <Column val="3"/>
                  <Type val="R"/>
                  <IsParameter val="N"/>
                  <_DitIndexForToolkit val="30"/>
                  <DIFF_UPDATE val="T"/>
                  <Condition val="Y"/>
                  <Modifier val="S"/>
                  <Direction val="C"/>
                </Select>
              </LogicLine>
              <LogicLine>
                <Select FieldID="5" FlowIsn="7" id="5">
                  <Column val="4"/>
                  <Type val="R"/>
                  <IsParameter val="N"/>
                  <_DitIndexForToolkit val="31"/>
                  <DIFF_UPDATE val="T"/>
                  <Condition val="Y"/>
                  <Modifier val="S"/>
                  <Direction val="C"/>
                </Select>
              </LogicLine>
              <LogicLine>
                <Select FieldID="6" FlowIsn="8" id="6">
                  <Column val="5"/>
                  <Type val="R"/>
                  <IsParameter val="N"/>
                  <_DitIndexForToolkit val="32"/>
                  <DIFF_UPDATE val="T"/>
                  <Condition val="Y"/>
                  <Modifier val="S"/>
                  <Direction val="C"/>
                </Select>
              </LogicLine>
              <LogicLine>
                <Select FieldID="7" FlowIsn="9" id="7">
                  <Column val="6"/>
                  <Type val="R"/>
                  <IsParameter val="N"/>
                  <_DitIndexForToolkit val="33"/>
                  <DIFF_UPDATE val="T"/>
                  <Condition val="Y"/>
                  <Modifier val="S"/>
                  <Direction val="C"/>
                </Select>
              </LogicLine>
              <LogicLine>
                <Select FieldID="8" FlowIsn="10" id="8">
                  <Column val="29"/>
                  <Type val="R"/>
                  <IsParameter val="N"/>
                  <_DitIndexForToolkit val="34"/>
                  <DIFF_UPDATE val="T"/>
                  <Condition val="Y"/>
                  <Modifier val="S"/>
                  <Direction val="C"/>
                </Select>
              </LogicLine>
              <LogicLine>
                <Select FieldID="9" FlowIsn="11" id="9">
                  <Column val="30"/>
                  <Type val="R"/>
                  <IsParameter val="N"/>
                  <_DitIndexForToolkit val="35"/>
                  <DIFF_UPDATE val="T"/>
                  <Condition val="Y"/>
                  <Modifier val="S"/>
                  <Direction val="C"/>
                </Select>
              </LogicLine>
              <LogicLine>
                <Select FieldID="10" FlowIsn="12" id="10">
                  <Column val="31"/>
                  <Type val="R"/>
                  <IsParameter val="N"/>
                  <_DitIndexForToolkit val="36"/>
                  <DIFF_UPDATE val="T"/>
                  <Condition val="Y"/>
                  <Modifier val="S"/>
                  <Direction val="C"/>
                </Select>
              </LogicLine>
              <LogicLine>
                <Select FieldID="11" FlowIsn="13" id="11">
                  <Column val="32"/>
                  <Type val="R"/>
                  <IsParameter val="N"/>
                  <_DitIndexForToolkit val="37"/>
                  <DIFF_UPDATE val="T"/>
                  <Condition val="Y"/>
                  <Modifier val="S"/>
                  <Direction val="C"/>
                </Select>
              </LogicLine>
              <LogicLine>
                <Select FieldID="12" FlowIsn="14" id="12">
                  <Column val="33"/>
                  <Type val="R"/>
                  <IsParameter val="N"/>
                  <_DitIndexForToolkit val="38"/>
                  <DIFF_UPDATE val="T"/>
                  <Condition val="Y"/>
                  <Modifier val="S"/>
                  <Direction val="C"/>
                </Select>
              </LogicLine>
              <LogicLine>
                <Select FieldID="13" FlowIsn="15" id="13">
                  <Column val="34"/>
                  <Type val="R"/>
                  <IsParameter val="N"/>
                  <_DitIndexForToolkit val="39"/>
                  <DIFF_UPDATE val="T"/>
                  <Condition val="Y"/>
                  <Modifier val="S"/>
                  <Direction val="C"/>
                </Select>
              </LogicLine>
              <LogicLine>
                <Select FieldID="14" FlowIsn="16" id="14">
                  <Column val="35"/>
                  <Type val="R"/>
                  <IsParameter val="N"/>
                  <_DitIndexForToolkit val="40"/>
                  <DIFF_UPDATE val="T"/>
                  <Condition val="Y"/>
                  <Modifier val="S"/>
                  <Direction val="C"/>
                </Select>
              </LogicLine>
              <LogicLine>
                <Select FieldID="15" FlowIsn="17" id="15">
                  <Column val="36"/>
                  <Type val="R"/>
                  <IsParameter val="N"/>
                  <_DitIndexForToolkit val="41"/>
                  <DIFF_UPDATE val="T"/>
                  <Condition val="Y"/>
                  <Modifier val="S"/>
                  <Direction val="C"/>
                </Select>
              </LogicLine>
              <LogicLine>
                <Select FieldID="16" FlowIsn="18" id="16">
                  <Column val="37"/>
                  <Type val="R"/>
                  <IsParameter val="N"/>
                  <_DitIndexForToolkit val="42"/>
                  <DIFF_UPDATE val="T"/>
                  <Condition val="Y"/>
                  <Modifier val="S"/>
                  <Direction val="C"/>
                </Select>
              </LogicLine>
              <LogicLine>
                <Select FieldID="17" FlowIsn="19" id="17">
                  <Column val="38"/>
                  <Type val="R"/>
                  <IsParameter val="N"/>
                  <_DitIndexForToolkit val="43"/>
                  <DIFF_UPDATE val="T"/>
                  <Condition val="Y"/>
                  <Modifier val="S"/>
                  <Direction val="C"/>
                </Select>
              </LogicLine>
              <LogicLine>
                <Select FieldID="18" FlowIsn="20" id="18">
                  <Column val="39"/>
                  <Type val="R"/>
                  <IsParameter val="N"/>
                  <_DitIndexForToolkit val="44"/>
                  <DIFF_UPDATE val="T"/>
                  <Condition val="Y"/>
                  <Modifier val="S"/>
                  <Direction val="C"/>
                </Select>
              </LogicLine>
              <LogicLine>
                <Select FieldID="19" FlowIsn="21" id="19">
                  <Column val="40"/>
                  <Type val="R"/>
                  <IsParameter val="N"/>
                  <_DitIndexForToolkit val="45"/>
                  <DIFF_UPDATE val="T"/>
                  <Condition val="Y"/>
                  <Modifier val="S"/>
                  <Direction val="C"/>
                </Select>
              </LogicLine>
              <LogicLine>
                <Select FieldID="20" FlowIsn="22" id="20">
                  <Column val="41"/>
                  <Type val="R"/>
                  <IsParameter val="N"/>
                  <_DitIndexForToolkit val="46"/>
                  <DIFF_UPDATE val="T"/>
                  <Condition val="Y"/>
                  <Modifier val="S"/>
                  <Direction val="C"/>
                </Select>
              </LogicLine>
              <LogicLine>
                <Select FieldID="21" FlowIsn="23" id="21">
                  <Column val="42"/>
                  <Type val="R"/>
                  <IsParameter val="N"/>
                  <_DitIndexForToolkit val="47"/>
                  <DIFF_UPDATE val="T"/>
                  <Condition val="Y"/>
                  <Modifier val="S"/>
                  <Direction val="C"/>
                </Select>
              </LogicLine>
              <LogicLine>
                <Select FieldID="22" FlowIsn="24" id="22">
                  <Column val="43"/>
                  <Type val="R"/>
                  <IsParameter val="N"/>
                  <_DitIndexForToolkit val="48"/>
                  <DIFF_UPDATE val="T"/>
                  <Condition val="Y"/>
                  <Modifier val="S"/>
                  <Direction val="C"/>
                </Select>
              </LogicLine>
              <LogicLine>
                <Select FieldID="23" FlowIsn="25" id="23">
                  <ASS val="1"/>
                  <Column val="44"/>
                  <Type val="R"/>
                  <IsParameter val="N"/>
                  <_DitIndexForToolkit val="49"/>
                  <DIFF_UPDATE val="T"/>
                  <Condition val="Y"/>
                  <Modifier val="S"/>
                  <Direction val="C"/>
                </Select>
              </LogicLine>
              <LogicLine>
                <Select FieldID="24" FlowIsn="26" id="24">
                  <Column val="45"/>
                  <Type val="R"/>
                  <IsParameter val="N"/>
                  <_DitIndexForToolkit val="50"/>
                  <DIFF_UPDATE val="T"/>
                  <Condition val="Y"/>
                  <Modifier val="S"/>
                  <Direction val="C"/>
                </Select>
              </LogicLine>
              <LogicLine>
                <Select FieldID="25" FlowIsn="27" id="25">
                  <Column val="46"/>
                  <Type val="R"/>
                  <IsParameter val="N"/>
                  <_DitIndexForToolkit val="51"/>
                  <DIFF_UPDATE val="T"/>
                  <Condition val="Y"/>
                  <Modifier val="S"/>
                  <Direction val="C"/>
                </Select>
              </LogicLine>
            </LogicLines>
          </LogicUnit>
          <LogicUnit id="3" propagate="78">
            <Level val="T"/>
            <Type val="P"/>
            <_DspTemplate val="0"/>
            <_HeaderPosition val="14"/>
            <Scope val="S"/>
            <EngineDirective val="S"/>
            <ShowMessage val="Y"/>
            <Condition val="89"/>
            <Event>
              <EventType val="S"/>
              <PublicObject comp="-1"/>
            </Event>
            <Expanded val="1"/>
            <LogicLines>
              <LogicLine>
                <CallTask FlowIsn="28">
                  <OperationType val="P"/>
                  <TaskID comp="-1" obj="979"/>
                  <Lock val="N"/>
                  <Arguments>
                    <Argument>
                      <id val="1"/>
                      <Expression val="3"/>
                      <Skip val="N"/>
                    </Argument>
                    <Argument>
                      <id val="2"/>
                      <Expression val="4"/>
                      <Skip val="N"/>
                    </Argument>
                    <Argument>
                      <id val="3"/>
                      <Expression val="1"/>
                      <Skip val="N"/>
                    </Argument>
                    <Argument>
                      <id val="4"/>
                      <Expression val="2"/>
                      <Skip val="N"/>
                    </Argument>
                    <Argument>
                      <id val="5"/>
                      <Expression val="5"/>
                      <Skip val="N"/>
                    </Argument>
                  </Arguments>
                  <Wait val="Y"/>
                  <SyncData val="N"/>
                  <RetainFocus val="N"/>
                  <Condition val="Y"/>
                  <Modifier val="S"/>
                  <Direction val="C"/>
                </CallTask>
              </LogicLine>
            </LogicLines>
          </LogicUnit>
          <LogicUnit id="4" propagate="78">
            <Level val="T"/>
            <Type val="S"/>
            <_DspTemplate val="0"/>
            <_HeaderPosition val="15"/>
            <Scope val="S"/>
            <EngineDirective val="S"/>
            <ShowMessage val="Y"/>
            <Condition val="89"/>
            <Event>
              <EventType val="S"/>
              <PublicObject comp="-1"/>
            </Event>
            <Expanded val="1"/>
            <LogicLines>
              <LogicLine>
                <CallTask FlowIsn="29">
                  <OperationType val="P"/>
                  <TaskID comp="-1" obj="979"/>
                  <Lock val="N"/>
                  <Arguments>
                    <Argument>
                      <id val="6"/>
                      <Expression val="3"/>
                      <Skip val="N"/>
                    </Argument>
                    <Argument>
                      <id val="7"/>
                      <Expression val="4"/>
                      <Skip val="N"/>
                    </Argument>
                    <Argument>
                      <id val="8"/>
                      <Expression val="1"/>
                      <Skip val="N"/>
                    </Argument>
                    <Argument>
                      <id val="9"/>
                      <Expression val="2"/>
                      <Skip val="N"/>
                    </Argument>
                    <Argument>
                      <id val="10"/>
                      <Expression val="6"/>
                      <Skip val="N"/>
                    </Argument>
                  </Arguments>
                  <Wait val="Y"/>
                  <SyncData val="N"/>
                  <RetainFocus val="N"/>
                  <Condition val="Y"/>
                  <Modifier val="B"/>
                  <Direction val="C"/>
                </CallTask>
              </LogicLine>
            </LogicLines>
          </LogicUnit>
          <LogicUnit id="5" propagate="78">
            <Level val="R"/>
            <Type val="S"/>
            <_DspTemplate val="0"/>
            <_HeaderPosition val="14"/>
            <Scope val="S"/>
            <EngineDirective val="S"/>
            <ShowMessage val="Y"/>
            <Condition val="89"/>
            <Event>
              <EventType val="S"/>
              <PublicObject comp="-1"/>
            </Event>
            <Expanded val="1"/>
            <LogicLines>
              <LogicLine>
                <Update FlowIsn="30">
                  <FieldID val="23"/>
                  <WithValue val="1"/>
                  <Incremental val="N"/>
                  <ForcedUpdate val="Y"/>
                  <Condition val="Y"/>
                  <Modifier val="B"/>
                  <Direction val="C"/>
                </Update>
              </LogicLine>
              <LogicLine>
                <Update FlowIsn="31">
                  <FieldID val="25"/>
                  <WithValue val="4"/>
                  <Incremental val="N"/>
                  <ForcedUpdate val="Y"/>
                  <Condition val="Y"/>
                  <Modifier val="B"/>
                  <Direction val="C"/>
                </Update>
              </LogicLine>
            </LogicLines>
          </LogicUnit>
        </TaskLogic>
        <TaskForms>
          <FormEntry _last_isn="51" _last_test_id="76" id="1">
            <PropertyList model="FORM_GUI0">
              <Model comp="-1" id="1" obj="133"/>
              <_Comment id="218"/>
              <FormName id="311" valUnicode="目標マスタ保守"/>
              <_TabbingOrder id="318" val="1"/>
            </PropertyList>
            <Control _test_id="26" id="1">
              <PropertyList model="CTRL_GUI0_TABLE">
                <Model comp="-1" id="1" obj="139"/>
                <Y id="22" val="6"/>
                <Width id="23" val="1772"/>
                <Height id="24" val="384"/>
                <TitleHeight id="79" val="12"/>
                <RowHeight id="80" val="14"/>
                <Elements id="81" val="25"/>
                <_WindowWidth id="241" val="672"/>
                <TitleColor id="677" val="150"/>
              </PropertyList>
            </Control>
            <Control ISN_FATHER="1" PDOD="128" _test_id="28" id="2">
              <PropertyList model="CTRL_GUI0_COLUMN">
                <Width id="23" val="56"/>
                <ControlLayer id="25" val="1"/>
                <Font id="50" val="140"/>
                <Color id="51" val="150"/>
                <Sortable id="134" val="Y"/>
                <ColumnTitle id="139" valUnicode="MOK 取引部門"/>
              </PropertyList>
            </Control>
            <Control ISN_FATHER="1" PDOD="128" _test_id="30" id="3">
              <PropertyList model="CTRL_GUI0_COLUMN">
                <Width id="23" val="59"/>
                <ControlLayer id="25" val="2"/>
                <Font id="50" val="140"/>
                <Color id="51" val="150"/>
                <ColumnTitle id="139" valUnicode="MOK マスタ種類"/>
              </PropertyList>
            </Control>
            <Control ISN_FATHER="1" PDOD="128" _test_id="32" id="4">
              <PropertyList model="CTRL_GUI0_COLUMN">
                <Width id="23" val="59"/>
                <ControlLayer id="25" val="3"/>
                <Font id="50" val="140"/>
                <Color id="51" val="150"/>
                <ColumnTitle id="139" valUnicode="MOK マスタ区分"/>
              </PropertyList>
            </Control>
            <Control ISN_FATHER="1" PDOD="128" _test_id="34" id="5">
              <PropertyList model="CTRL_GUI0_COLUMN">
                <Width id="23" val="67"/>
                <ControlLayer id="25" val="4"/>
                <Font id="50" val="140"/>
                <Color id="51" val="150"/>
                <ColumnTitle id="139" valUnicode="MOK 取引先コード"/>
              </PropertyList>
            </Control>
            <Control ISN_FATHER="1" PDOD="128" _test_id="36" id="6">
              <PropertyList model="CTRL_GUI0_COLUMN">
                <Width id="23" val="48"/>
                <ControlLayer id="25" val="5"/>
                <Font id="50" val="140"/>
                <Color id="51" val="150"/>
                <ColumnTitle id="139" valUnicode="MOK 年月"/>
              </PropertyList>
            </Control>
            <Control ISN_FATHER="1" PDOD="128" _test_id="38" id="7">
              <PropertyList model="CTRL_GUI0_COLUMN">
                <Width id="23" val="72"/>
                <ControlLayer id="25" val="6"/>
                <Font id="50" val="140"/>
                <Color id="51" val="150"/>
                <ColumnTitle id="139" valUnicode="MOK 純売目標"/>
              </PropertyList>
            </Control>
            <Control ISN_FATHER="1" PDOD="128" _test_id="40" id="8">
              <PropertyList model="CTRL_GUI0_COLUMN">
                <Width id="23" val="72"/>
                <ControlLayer id="25" val="7"/>
                <Font id="50" val="140"/>
                <Color id="51" val="150"/>
                <ColumnTitle id="139" valUnicode="MOK 粗利目標"/>
              </PropertyList>
            </Control>
            <Control ISN_FATHER="1" PDOD="128" _test_id="42" id="9">
              <PropertyList model="CTRL_GUI0_COLUMN">
                <Width id="23" val="59"/>
                <ControlLayer id="25" val="8"/>
                <Font id="50" val="140"/>
                <Color id="51" val="150"/>
                <ColumnTitle id="139" valUnicode="MOK 予備区分１"/>
              </PropertyList>
            </Control>
            <Control ISN_FATHER="1" PDOD="128" _test_id="44" id="10">
              <PropertyList model="CTRL_GUI0_COLUMN">
                <Width id="23" val="59"/>
                <ControlLayer id="25" val="9"/>
                <Font id="50" val="140"/>
                <Color id="51" val="150"/>
                <ColumnTitle id="139" valUnicode="MOK 予備区分２"/>
              </PropertyList>
            </Control>
            <Control ISN_FATHER="1" PDOD="128" _test_id="46" id="11">
              <PropertyList model="CTRL_GUI0_COLUMN">
                <Width id="23" val="59"/>
                <ControlLayer id="25" val="10"/>
                <Font id="50" val="140"/>
                <Color id="51" val="150"/>
                <ColumnTitle id="139" valUnicode="MOK 予備区分３"/>
              </PropertyList>
            </Control>
            <Control ISN_FATHER="1" PDOD="128" _test_id="48" id="12">
              <PropertyList model="CTRL_GUI0_COLUMN">
                <Width id="23" val="68"/>
                <ControlLayer id="25" val="11"/>
                <Font id="50" val="140"/>
                <Color id="51" val="150"/>
                <ColumnTitle id="139" valUnicode="MOK 予備金額１"/>
              </PropertyList>
            </Control>
            <Control ISN_FATHER="1" PDOD="128" _test_id="50" id="13">
              <PropertyList model="CTRL_GUI0_COLUMN">
                <Width id="23" val="68"/>
                <ControlLayer id="25" val="12"/>
                <Font id="50" val="140"/>
                <Color id="51" val="150"/>
                <ColumnTitle id="139" valUnicode="MOK 予備金額２"/>
              </PropertyList>
            </Control>
            <Control ISN_FATHER="1" PDOD="128" _test_id="52" id="14">
              <PropertyList model="CTRL_GUI0_COLUMN">
                <Width id="23" val="68"/>
                <ControlLayer id="25" val="13"/>
                <Font id="50" val="140"/>
                <Color id="51" val="150"/>
                <ColumnTitle id="139" valUnicode="MOK 予備金額３"/>
              </PropertyList>
            </Control>
            <Control ISN_FATHER="1" PDOD="128" _test_id="54" id="15">
              <PropertyList model="CTRL_GUI0_COLUMN">
                <Width id="23" val="68"/>
                <ControlLayer id="25" val="14"/>
                <Font id="50" val="140"/>
                <Color id="51" val="150"/>
                <ColumnTitle id="139" valUnicode="MOK 予備数量１"/>
              </PropertyList>
            </Control>
            <Control ISN_FATHER="1" PDOD="128" _test_id="56" id="16">
              <PropertyList model="CTRL_GUI0_COLUMN">
                <Width id="23" val="68"/>
                <ControlLayer id="25" val="15"/>
                <Font id="50" val="140"/>
                <Color id="51" val="150"/>
                <ColumnTitle id="139" valUnicode="MOK 予備数量２"/>
              </PropertyList>
            </Control>
            <Control ISN_FATHER="1" PDOD="128" _test_id="58" id="17">
              <PropertyList model="CTRL_GUI0_COLUMN">
                <Width id="23" val="68"/>
                <ControlLayer id="25" val="16"/>
                <Font id="50" val="140"/>
                <Color id="51" val="150"/>
                <ColumnTitle id="139" valUnicode="MOK 予備数量３"/>
              </PropertyList>
            </Control>
            <Control ISN_FATHER="1" PDOD="128" _test_id="60" id="18">
              <PropertyList model="CTRL_GUI0_COLUMN">
                <Width id="23" val="120"/>
                <ControlLayer id="25" val="17"/>
                <Font id="50" val="140"/>
                <Color id="51" val="150"/>
                <ColumnTitle id="139" valUnicode="MOK 予備文字１"/>
              </PropertyList>
            </Control>
            <Control ISN_FATHER="1" PDOD="128" _test_id="62" id="19">
              <PropertyList model="CTRL_GUI0_COLUMN">
                <Width id="23" val="120"/>
                <ControlLayer id="25" val="18"/>
                <Font id="50" val="140"/>
                <Color id="51" val="150"/>
                <ColumnTitle id="139" valUnicode="MOK 予備文字２"/>
              </PropertyList>
            </Control>
            <Control ISN_FATHER="1" PDOD="128" _test_id="64" id="20">
              <PropertyList model="CTRL_GUI0_COLUMN">
                <Width id="23" val="120"/>
                <ControlLayer id="25" val="19"/>
                <Font id="50" val="140"/>
                <Color id="51" val="150"/>
                <ColumnTitle id="139" valUnicode="MOK 予備文字３"/>
              </PropertyList>
            </Control>
            <Control ISN_FATHER="1" PDOD="128" _test_id="66" id="21">
              <PropertyList model="CTRL_GUI0_COLUMN">
                <Width id="23" val="52"/>
                <ControlLayer id="25" val="20"/>
                <Font id="50" val="140"/>
                <Color id="51" val="150"/>
                <ColumnTitle id="139" valUnicode="MOK 予備日付１"/>
              </PropertyList>
            </Control>
            <Control ISN_FATHER="1" PDOD="128" _test_id="68" id="22">
              <PropertyList model="CTRL_GUI0_COLUMN">
                <Width id="23" val="52"/>
                <ControlLayer id="25" val="21"/>
                <Font id="50" val="140"/>
                <Color id="51" val="150"/>
                <ColumnTitle id="139" valUnicode="MOK 予備日付２"/>
              </PropertyList>
            </Control>
            <Control ISN_FATHER="1" PDOD="128" _test_id="70" id="23">
              <PropertyList model="CTRL_GUI0_COLUMN">
                <Width id="23" val="52"/>
                <ControlLayer id="25" val="22"/>
                <Font id="50" val="140"/>
                <Color id="51" val="150"/>
                <ColumnTitle id="139" valUnicode="MOK 予備日付３"/>
              </PropertyList>
            </Control>
            <Control ISN_FATHER="1" PDOD="128" _test_id="72" id="24">
              <PropertyList model="CTRL_GUI0_COLUMN">
                <Width id="23" val="52"/>
                <ControlLayer id="25" val="23"/>
                <Font id="50" val="140"/>
                <Color id="51" val="150"/>
                <ColumnTitle id="139" valUnicode="MOK 登録日"/>
              </PropertyList>
            </Control>
            <Control ISN_FATHER="1" PDOD="128" _test_id="74" id="25">
              <PropertyList model="CTRL_GUI0_COLUMN">
                <Width id="23" val="52"/>
                <ControlLayer id="25" val="24"/>
                <Font id="50" val="140"/>
                <Color id="51" val="150"/>
                <ColumnTitle id="139" valUnicode="MOK 修正日"/>
              </PropertyList>
            </Control>
            <Control ISN_FATHER="1" PDOD="128" _test_id="76" id="26">
              <PropertyList model="CTRL_GUI0_COLUMN">
                <Width id="23" val="120"/>
                <ControlLayer id="25" val="25"/>
                <Font id="50" val="140"/>
                <Color id="51" val="150"/>
                <ColumnTitle id="139" valUnicode="MOK 最終更新ＰＧ"/>
              </PropertyList>
            </Control>
            <Control ISN_FATHER="1" PDOD="1" _test_id="27" id="27">
              <PropertyList model="CTRL_GUI0_EDIT">
                <Model comp="-1" id="1" obj="141"/>
                <Placement bottom="100" id="20" right="100"/>
                <X id="21" val="2"/>
                <Y id="22" val="21"/>
                <Width id="23" val="52"/>
                <Height id="24" val="10"/>
                <ControlLayer id="25" val="1"/>
                <Data FieldID="1" id="43"/>
                <ControlName id="46" val="MOK 取引部門"/>
                <Font id="50" val="139"/>
                <Style id="63" val="1"/>
                <MultiLineEdit id="71"/>
                <_Orientation id="143"/>
                <TabOrder id="314" val="1"/>
                <Border id="452"/>
              </PropertyList>
            </Control>
            <Control ISN_FATHER="1" PDOD="1" _test_id="29" id="28">
              <PropertyList model="CTRL_GUI0_EDIT">
                <Model comp="-1" id="1" obj="141"/>
                <Placement bottom="100" id="20" right="100"/>
                <X id="21" val="58"/>
                <Y id="22" val="21"/>
                <Width id="23" val="55"/>
                <Height id="24" val="10"/>
                <ControlLayer id="25" val="2"/>
                <Data FieldID="2" id="43"/>
                <ControlName id="46" val="MOK マスタ種類"/>
                <Font id="50" val="139"/>
                <Style id="63" val="1"/>
                <MultiLineEdit id="71"/>
                <_Orientation id="143"/>
                <TabOrder id="314" val="2"/>
                <Border id="452"/>
              </PropertyList>
            </Control>
            <Control ISN_FATHER="1" PDOD="1" _test_id="31" id="29">
              <PropertyList model="CTRL_GUI0_EDIT">
                <Model comp="-1" id="1" obj="141"/>
                <Placement bottom="100" id="20" right="100"/>
                <X id="21" val="117"/>
                <Y id="22" val="21"/>
                <Width id="23" val="55"/>
                <Height id="24" val="10"/>
                <ControlLayer id="25" val="3"/>
                <Data FieldID="3" id="43"/>
                <ControlName id="46" val="MOK マスタ区分"/>
                <Font id="50" val="139"/>
                <Style id="63" val="1"/>
                <MultiLineEdit id="71"/>
                <_Orientation id="143"/>
                <TabOrder id="314" val="3"/>
                <Border id="452"/>
              </PropertyList>
            </Control>
            <Control ISN_FATHER="1" PDOD="1" _test_id="33" id="30">
              <PropertyList model="CTRL_GUI0_EDIT">
                <Model comp="-1" id="1" obj="141"/>
                <Placement bottom="100" id="20" right="100"/>
                <X id="21" val="176"/>
                <Y id="22" val="21"/>
                <Width id="23" val="64"/>
                <Height id="24" val="10"/>
                <ControlLayer id="25" val="4"/>
                <Data FieldID="4" id="43"/>
                <ControlName id="46" val="MOK 取引先コード"/>
                <Font id="50" val="139"/>
                <Style id="63" val="1"/>
                <MultiLineEdit id="71"/>
                <_Orientation id="143"/>
                <TabOrder id="314" val="4"/>
                <Border id="452"/>
              </PropertyList>
            </Control>
            <Control ISN_FATHER="1" PDOD="128" _test_id="35" id="31">
              <PropertyList model="CTRL_GUI0_EDIT">
                <Model comp="-1" id="1" obj="141"/>
                <Placement bottom="100" id="20" right="100"/>
                <X id="21" val="243"/>
                <Y id="22" val="21"/>
                <Width id="23" val="43"/>
                <Height id="24" val="10"/>
                <ControlLayer id="25" val="5"/>
                <Data FieldID="5" id="43"/>
                <ControlName id="46" val="MOK 年月"/>
                <Font id="50" val="139"/>
                <Style id="63" val="1"/>
                <HorizontalAlignment id="65" val="2"/>
                <MultiLineEdit id="71"/>
                <Format id="82" valUnicode="##/##/##Z"/>
                <_Orientation id="143"/>
                <TabOrder id="314" val="5"/>
                <Border id="452"/>
              </PropertyList>
            </Control>
            <Control ISN_FATHER="1" PDOD="2" _test_id="37" id="32">
              <PropertyList model="CTRL_GUI0_EDIT">
                <Model comp="-1" id="1" obj="141"/>
                <Placement bottom="100" id="20" right="100"/>
                <X id="21" val="291"/>
                <Y id="22" val="21"/>
                <Width id="23" val="65"/>
                <Height id="24" val="10"/>
                <ControlLayer id="25" val="6"/>
                <Data FieldID="6" id="43"/>
                <ControlName id="46" val="MOK 純売目標"/>
                <Font id="50" val="139"/>
                <Style id="63" val="1"/>
                <MultiLineEdit id="71"/>
                <_Orientation id="143"/>
                <TabOrder id="314" val="6"/>
                <Border id="452"/>
              </PropertyList>
            </Control>
            <Control ISN_FATHER="1" PDOD="2" _test_id="39" id="33">
              <PropertyList model="CTRL_GUI0_EDIT">
                <Model comp="-1" id="1" obj="141"/>
                <Placement bottom="100" id="20" right="100"/>
                <X id="21" val="363"/>
                <Y id="22" val="21"/>
                <Width id="23" val="65"/>
                <Height id="24" val="10"/>
                <ControlLayer id="25" val="7"/>
                <Data FieldID="7" id="43"/>
                <ControlName id="46" val="MOK 粗利目標"/>
                <Font id="50" val="139"/>
                <Style id="63" val="1"/>
                <MultiLineEdit id="71"/>
                <_Orientation id="143"/>
                <TabOrder id="314" val="7"/>
                <Border id="452"/>
              </PropertyList>
            </Control>
            <Control ISN_FATHER="1" PDOD="1" _test_id="41" id="34">
              <PropertyList model="CTRL_GUI0_EDIT">
                <Model comp="-1" id="1" obj="141"/>
                <Placement bottom="100" id="20" right="100"/>
                <X id="21" val="435"/>
                <Y id="22" val="21"/>
                <Width id="23" val="57"/>
                <Height id="24" val="10"/>
                <ControlLayer id="25" val="8"/>
                <Data FieldID="8" id="43"/>
                <ControlName id="46" val="MOK 予備区分１"/>
                <Font id="50" val="139"/>
                <Style id="63" val="1"/>
                <MultiLineEdit id="71"/>
                <_Orientation id="143"/>
                <TabOrder id="314" val="8"/>
                <Border id="452"/>
              </PropertyList>
            </Control>
            <Control ISN_FATHER="1" PDOD="1" _test_id="43" id="35">
              <PropertyList model="CTRL_GUI0_EDIT">
                <Model comp="-1" id="1" obj="141"/>
                <Placement bottom="100" id="20" right="100"/>
                <X id="21" val="494"/>
                <Y id="22" val="21"/>
                <Width id="23" val="57"/>
                <Height id="24" val="10"/>
                <ControlLayer id="25" val="9"/>
                <Data FieldID="9" id="43"/>
                <ControlName id="46" val="MOK 予備区分２"/>
                <Font id="50" val="139"/>
                <Style id="63" val="1"/>
                <MultiLineEdit id="71"/>
                <_Orientation id="143"/>
                <TabOrder id="314" val="9"/>
                <Border id="452"/>
              </PropertyList>
            </Control>
            <Control ISN_FATHER="1" PDOD="1" _test_id="45" id="36">
              <PropertyList model="CTRL_GUI0_EDIT">
                <Model comp="-1" id="1" obj="141"/>
                <Placement bottom="100" id="20" right="100"/>
                <X id="21" val="553"/>
                <Y id="22" val="21"/>
                <Width id="23" val="57"/>
                <Height id="24" val="10"/>
                <ControlLayer id="25" val="10"/>
                <Data FieldID="10" id="43"/>
                <ControlName id="46" val="MOK 予備区分３"/>
                <Font id="50" val="139"/>
                <Style id="63" val="1"/>
                <MultiLineEdit id="71"/>
                <_Orientation id="143"/>
                <TabOrder id="314" val="10"/>
                <Border id="452"/>
              </PropertyList>
            </Control>
            <Control ISN_FATHER="1" PDOD="2" _test_id="47" id="37">
              <PropertyList model="CTRL_GUI0_EDIT">
                <Model comp="-1" id="1" obj="141"/>
                <Placement bottom="100" id="20" right="100"/>
                <X id="21" val="612"/>
                <Y id="22" val="21"/>
                <Width id="23" val="66"/>
                <Height id="24" val="10"/>
                <ControlLayer id="25" val="11"/>
                <Data FieldID="11" id="43"/>
                <ControlName id="46" val="MOK 予備金額１"/>
                <Font id="50" val="139"/>
                <Style id="63" val="1"/>
                <MultiLineEdit id="71"/>
                <_Orientation id="143"/>
                <TabOrder id="314" val="11"/>
                <Border id="452"/>
              </PropertyList>
            </Control>
            <Control ISN_FATHER="1" PDOD="2" _test_id="49" id="38">
              <PropertyList model="CTRL_GUI0_EDIT">
                <Model comp="-1" id="1" obj="141"/>
                <Placement bottom="100" id="20" right="100"/>
                <X id="21" val="680"/>
                <Y id="22" val="21"/>
                <Width id="23" val="66"/>
                <Height id="24" val="10"/>
                <ControlLayer id="25" val="12"/>
                <Data FieldID="12" id="43"/>
                <ControlName id="46" val="MOK 予備金額２"/>
                <Font id="50" val="139"/>
                <Style id="63" val="1"/>
                <MultiLineEdit id="71"/>
                <_Orientation id="143"/>
                <TabOrder id="314" val="12"/>
                <Border id="452"/>
              </PropertyList>
            </Control>
            <Control ISN_FATHER="1" PDOD="2" _test_id="51" id="39">
              <PropertyList model="CTRL_GUI0_EDIT">
                <Model comp="-1" id="1" obj="141"/>
                <Placement bottom="100" id="20" right="100"/>
                <X id="21" val="748"/>
                <Y id="22" val="21"/>
                <Width id="23" val="66"/>
                <Height id="24" val="10"/>
                <ControlLayer id="25" val="13"/>
                <Data FieldID="13" id="43"/>
                <ControlName id="46" val="MOK 予備金額３"/>
                <Font id="50" val="139"/>
                <Style id="63" val="1"/>
                <MultiLineEdit id="71"/>
                <_Orientation id="143"/>
                <TabOrder id="314" val="13"/>
                <Border id="452"/>
              </PropertyList>
            </Control>
            <Control ISN_FATHER="1" PDOD="18" _test_id="53" id="40">
              <PropertyList model="CTRL_GUI0_EDIT">
                <Model comp="-1" id="1" obj="141"/>
                <Placement bottom="100" id="20" right="100"/>
                <X id="21" val="816"/>
                <Y id="22" val="21"/>
                <Width id="23" val="64"/>
                <Height id="24" val="10"/>
                <ControlLayer id="25" val="14"/>
                <Data FieldID="14" id="43"/>
                <ControlName id="46" val="MOK 予備数量１"/>
                <Font id="50" val="139"/>
                <Style id="63" val="1"/>
                <MultiLineEdit id="71"/>
                <_Orientation id="143"/>
                <TabOrder id="314" val="14"/>
                <Border id="452"/>
              </PropertyList>
            </Control>
            <Control ISN_FATHER="1" PDOD="18" _test_id="55" id="41">
              <PropertyList model="CTRL_GUI0_EDIT">
                <Model comp="-1" id="1" obj="141"/>
                <Placement bottom="100" id="20" right="100"/>
                <X id="21" val="884"/>
                <Y id="22" val="21"/>
                <Width id="23" val="64"/>
                <Height id="24" val="10"/>
                <ControlLayer id="25" val="15"/>
                <Data FieldID="15" id="43"/>
                <ControlName id="46" val="MOK 予備数量２"/>
                <Font id="50" val="139"/>
                <Style id="63" val="1"/>
                <MultiLineEdit id="71"/>
                <_Orientation id="143"/>
                <TabOrder id="314" val="15"/>
                <Border id="452"/>
              </PropertyList>
            </Control>
            <Control ISN_FATHER="1" PDOD="18" _test_id="57" id="42">
              <PropertyList model="CTRL_GUI0_EDIT">
                <Model comp="-1" id="1" obj="141"/>
                <Placement bottom="100" id="20" right="100"/>
                <X id="21" val="952"/>
                <Y id="22" val="21"/>
                <Width id="23" val="64"/>
                <Height id="24" val="10"/>
                <ControlLayer id="25" val="16"/>
                <Data FieldID="16" id="43"/>
                <ControlName id="46" val="MOK 予備数量３"/>
                <Font id="50" val="139"/>
                <Style id="63" val="1"/>
                <MultiLineEdit id="71"/>
                <_Orientation id="143"/>
                <TabOrder id="314" val="16"/>
                <Border id="452"/>
              </PropertyList>
            </Control>
            <Control ISN_FATHER="1" _test_id="59" id="43">
              <PropertyList model="CTRL_GUI0_EDIT">
                <Model comp="-1" id="1" obj="141"/>
                <Placement bottom="100" id="20" right="100"/>
                <X id="21" val="1020"/>
                <Y id="22" val="21"/>
                <Width id="23" val="114"/>
                <Height id="24" val="10"/>
                <ControlLayer id="25" val="17"/>
                <Data FieldID="17" id="43"/>
                <ControlName id="46" val="MOK 予備文字１"/>
                <Font id="50" val="139"/>
                <Style id="63" val="1"/>
                <_Orientation id="143"/>
                <TabOrder id="314" val="17"/>
                <Border id="452"/>
              </PropertyList>
            </Control>
            <Control ISN_FATHER="1" _test_id="61" id="44">
              <PropertyList model="CTRL_GUI0_EDIT">
                <Model comp="-1" id="1" obj="141"/>
                <Placement bottom="100" id="20" right="100"/>
                <X id="21" val="1140"/>
                <Y id="22" val="21"/>
                <Width id="23" val="114"/>
                <Height id="24" val="10"/>
                <ControlLayer id="25" val="18"/>
                <Data FieldID="18" id="43"/>
                <ControlName id="46" val="MOK 予備文字２"/>
                <Font id="50" val="139"/>
                <Style id="63" val="1"/>
                <_Orientation id="143"/>
                <TabOrder id="314" val="18"/>
                <Border id="452"/>
              </PropertyList>
            </Control>
            <Control ISN_FATHER="1" _test_id="63" id="45">
              <PropertyList model="CTRL_GUI0_EDIT">
                <Model comp="-1" id="1" obj="141"/>
                <Placement bottom="100" id="20" right="100"/>
                <X id="21" val="1260"/>
                <Y id="22" val="21"/>
                <Width id="23" val="114"/>
                <Height id="24" val="10"/>
                <ControlLayer id="25" val="19"/>
                <Data FieldID="19" id="43"/>
                <ControlName id="46" val="MOK 予備文字３"/>
                <Font id="50" val="139"/>
                <Style id="63" val="1"/>
                <_Orientation id="143"/>
                <TabOrder id="314" val="19"/>
                <Border id="452"/>
              </PropertyList>
            </Control>
            <Control ISN_FATHER="1" PDOD="128" _test_id="65" id="46">
              <PropertyList model="CTRL_GUI0_EDIT">
                <Model comp="-1" id="1" obj="141"/>
                <Placement bottom="100" id="20" right="100"/>
                <X id="21" val="1380"/>
                <Y id="22" val="21"/>
                <Width id="23" val="49"/>
                <Height id="24" val="10"/>
                <ControlLayer id="25" val="20"/>
                <Data FieldID="20" id="43"/>
                <ControlName id="46" val="MOK 予備日付１"/>
                <Font id="50" val="139"/>
                <Style id="63" val="1"/>
                <HorizontalAlignment id="65" val="2"/>
                <MultiLineEdit id="71"/>
                <Format id="82" valUnicode="##/##/##Z"/>
                <_Orientation id="143"/>
                <TabOrder id="314" val="20"/>
                <Border id="452"/>
              </PropertyList>
            </Control>
            <Control ISN_FATHER="1" PDOD="128" _test_id="67" id="47">
              <PropertyList model="CTRL_GUI0_EDIT">
                <Model comp="-1" id="1" obj="141"/>
                <Placement bottom="100" id="20" right="100"/>
                <X id="21" val="1432"/>
                <Y id="22" val="21"/>
                <Width id="23" val="49"/>
                <Height id="24" val="10"/>
                <ControlLayer id="25" val="21"/>
                <Data FieldID="21" id="43"/>
                <ControlName id="46" val="MOK 予備日付２"/>
                <Font id="50" val="139"/>
                <Style id="63" val="1"/>
                <HorizontalAlignment id="65" val="2"/>
                <MultiLineEdit id="71"/>
                <Format id="82" valUnicode="##/##/##Z"/>
                <_Orientation id="143"/>
                <TabOrder id="314" val="21"/>
                <Border id="452"/>
              </PropertyList>
            </Control>
            <Control ISN_FATHER="1" PDOD="128" _test_id="69" id="48">
              <PropertyList model="CTRL_GUI0_EDIT">
                <Model comp="-1" id="1" obj="141"/>
                <Placement bottom="100" id="20" right="100"/>
                <X id="21" val="1484"/>
                <Y id="22" val="21"/>
                <Width id="23" val="49"/>
                <Height id="24" val="10"/>
                <ControlLayer id="25" val="22"/>
                <Data FieldID="22" id="43"/>
                <ControlName id="46" val="MOK 予備日付３"/>
                <Font id="50" val="139"/>
                <Style id="63" val="1"/>
                <HorizontalAlignment id="65" val="2"/>
                <MultiLineEdit id="71"/>
                <Format id="82" valUnicode="##/##/##Z"/>
                <_Orientation id="143"/>
                <TabOrder id="314" val="22"/>
                <Border id="452"/>
              </PropertyList>
            </Control>
            <Control ISN_FATHER="1" PDOD="128" _test_id="71" id="49">
              <PropertyList model="CTRL_GUI0_EDIT">
                <Model comp="-1" id="1" obj="141"/>
                <Placement bottom="100" id="20" right="100"/>
                <X id="21" val="1536"/>
                <Y id="22" val="21"/>
                <Width id="23" val="49"/>
                <Height id="24" val="10"/>
                <ControlLayer id="25" val="23"/>
                <Data FieldID="23" id="43"/>
                <ControlName id="46" val="MOK 登録日"/>
                <Font id="50" val="139"/>
                <Style id="63" val="1"/>
                <HorizontalAlignment id="65" val="2"/>
                <MultiLineEdit id="71"/>
                <Format id="82" valUnicode="##/##/##Z"/>
                <_Orientation id="143"/>
                <TabOrder id="314" val="23"/>
                <Border id="452"/>
              </PropertyList>
            </Control>
            <Control ISN_FATHER="1" PDOD="128" _test_id="73" id="50">
              <PropertyList model="CTRL_GUI0_EDIT">
                <Model comp="-1" id="1" obj="141"/>
                <Placement bottom="100" id="20" right="100"/>
                <X id="21" val="1588"/>
                <Y id="22" val="21"/>
                <Width id="23" val="49"/>
                <Height id="24" val="10"/>
                <ControlLayer id="25" val="24"/>
                <Data FieldID="24" id="43"/>
                <ControlName id="46" val="MOK 修正日"/>
                <Font id="50" val="139"/>
                <Style id="63" val="1"/>
                <HorizontalAlignment id="65" val="2"/>
                <MultiLineEdit id="71"/>
                <Format id="82" valUnicode="##/##/##Z"/>
                <_Orientation id="143"/>
                <TabOrder id="314" val="24"/>
                <Border id="452"/>
              </PropertyList>
            </Control>
            <Control ISN_FATHER="1" _test_id="75" id="51">
              <PropertyList model="CTRL_GUI0_EDIT">
                <Model comp="-1" id="1" obj="141"/>
                <Placement bottom="100" id="20" right="100"/>
                <X id="21" val="1640"/>
                <Y id="22" val="21"/>
                <Width id="23" val="114"/>
                <Height id="24" val="10"/>
                <ControlLayer id="25" val="25"/>
                <Data FieldID="25" id="43"/>
                <ControlName id="46" val="MOK 最終更新ＰＧ"/>
                <Font id="50" val="139"/>
                <Style id="63" val="1"/>
                <_Orientation id="143"/>
                <TabOrder id="314" val="25"/>
                <Border id="452"/>
              </PropertyList>
            </Control>
          </FormEntry>
        </TaskForms>
        <Expressions>
          <Expression id="1">
            <ExpSyntax val="Date()"/>
            <ExpAttribute val="D"/>
          </Expression>
          <Expression id="2">
            <ExpSyntax val="Time()"/>
            <ExpAttribute val="T"/>
          </Expression>
          <Expression id="3">
            <ExpSyntax val="Term()"/>
            <ExpAttribute val="N"/>
          </Expression>
          <Expression id="4">
            <ExpSyntax val="Prog()"/>
            <ExpAttribute val="A"/>
          </Expression>
          <Expression id="5">
            <ExpSyntax val="'S'"/>
            <ExpAttribute val="A"/>
          </Expression>
          <Expression id="6">
            <ExpSyntax val="'E'"/>
            <ExpAttribute val="A"/>
          </Expression>
        </Expressions>
      </Task>
    </Programs>
  </ProgramsRepository>

</Application>
