<?xml version="1.0" encoding="UTF-8" standalone="no" ?>
<Application>

  <Header>
    <Version val="12050"/>
    <WithIsn val="Y"/>
    <_InternalTask val="N"/>
    <IsRoot val="N"/>
    <InIndex val="N"/>
  </Header>

  <ProgramsRepository>
    <Programs>
      <Task MainProgram="N">
        <Header Description="ﾌﾟﾛﾃｸﾄﾁｪｯｸ(売上仕入)" ISN_2="1" LastIsn="1" id="338">
          <Public val="Protecte"/>
          <ExecutionRight comp="-1"/>
          <Resident val="N"/>
          <SQL val="N"/>
          <ReturnValue>
            <ReturnValueAttr/>
            <ParametersAttributes/>
          </ReturnValue>
          <SqlWhereExist val="N"/>
          <TaskType val="B"/>
          <External val="Y"/>
          <Offline val="N"/>
          <DotNetObjectExists val="N"/>
          <LastModified _date="732085" _time="61530" date="2005/05/19" time="17:05:30"/>
        </Header>
        <ItemIsn val="9"/>
        <Resource>
          <Columns>
            <Column id="10" name="P)管理FLG">
              <PropertyList model="FIELD">
                <Model attr_obj="FIELD_NUMERIC" id="1"/>
                <Picture id="157" valUnicode="1"/>
                <GuiDisplay id="158">
                  <PropertyList model="CTRL_GUI0_EDIT">
                    <Color id="51" val="1"/>
                  </PropertyList>
                </GuiDisplay>
                <GuiDisplayTable id="159">
                  <PropertyList model="CTRL_GUI0_EDIT">
                    <Color id="51" val="1"/>
                  </PropertyList>
                </GuiDisplayTable>
                <GuiOutput id="160">
                  <PropertyList model="CTRL_GUI1_EDIT">
                    <Color id="51" val="1"/>
                  </PropertyList>
                </GuiOutput>
                <GuiOutputTable id="161">
                  <PropertyList model="CTRL_GUI1_EDIT">
                    <Color id="51" val="1"/>
                  </PropertyList>
                </GuiOutputTable>
                <NullValue id="167" val="0"/>
                <StoredAs id="173" val="1"/>
                <Definition id="175" val="2"/>
                <UpdateStyle id="176" val="A"/>
                <_Dec id="181"/>
                <_Whole id="182" val="1"/>
                <_Negative id="192"/>
              </PropertyList>
            </Column>
            <Column id="11" name="P)デモFLG">
              <PropertyList model="FIELD">
                <Model attr_obj="FIELD_NUMERIC" id="1"/>
                <Picture id="157" valUnicode="1"/>
                <GuiDisplay id="158">
                  <PropertyList model="CTRL_GUI0_EDIT">
                    <Color id="51" val="1"/>
                    <Border id="452" val="Y"/>
                  </PropertyList>
                </GuiDisplay>
                <GuiDisplayTable id="159">
                  <PropertyList model="CTRL_GUI0_EDIT">
                    <Color id="51" val="1"/>
                    <Border id="452" val="Y"/>
                  </PropertyList>
                </GuiDisplayTable>
                <GuiOutput id="160">
                  <PropertyList model="CTRL_GUI1_EDIT">
                    <Color id="51" val="1"/>
                  </PropertyList>
                </GuiOutput>
                <GuiOutputTable id="161">
                  <PropertyList model="CTRL_GUI1_EDIT">
                    <Color id="51" val="1"/>
                  </PropertyList>
                </GuiOutputTable>
                <NullValue id="167" val="0"/>
                <StoredAs id="173" val="1"/>
                <Definition id="175" val="2"/>
                <UpdateStyle id="176" val="A"/>
                <_Dec id="181"/>
                <_Whole id="182" val="1"/>
                <_Negative id="192"/>
              </PropertyList>
            </Column>
            <Column id="12" name="V)hwkbsys">
              <PropertyList model="FIELD">
                <Model attr_obj="FIELD_NUMERIC" id="1"/>
                <Picture id="157" valUnicode="8"/>
                <GuiDisplay id="158">
                  <PropertyList model="CTRL_GUI0_EDIT">
                    <Color id="51" val="1"/>
                  </PropertyList>
                </GuiDisplay>
                <GuiDisplayTable id="159">
                  <PropertyList model="CTRL_GUI0_EDIT">
                    <Color id="51" val="1"/>
                  </PropertyList>
                </GuiDisplayTable>
                <GuiOutput id="160">
                  <PropertyList model="CTRL_GUI1_EDIT">
                    <Color id="51" val="1"/>
                  </PropertyList>
                </GuiOutput>
                <GuiOutputTable id="161">
                  <PropertyList model="CTRL_GUI1_EDIT">
                    <Color id="51" val="1"/>
                  </PropertyList>
                </GuiOutputTable>
                <NullValue id="167" val="0"/>
                <StoredAs id="173" val="1"/>
                <Definition id="175" val="2"/>
                <UpdateStyle id="176" val="A"/>
                <_Dec id="181"/>
                <_Whole id="182" val="8"/>
                <_Negative id="192"/>
              </PropertyList>
            </Column>
            <Column id="13" name="V)flCtrl">
              <PropertyList model="FIELD">
                <Model attr_obj="FIELD_NUMERIC" id="1"/>
                <Picture id="157" valUnicode="8"/>
                <GuiDisplay id="158">
                  <PropertyList model="CTRL_GUI0_EDIT">
                    <Color id="51" val="1"/>
                  </PropertyList>
                </GuiDisplay>
                <GuiDisplayTable id="159">
                  <PropertyList model="CTRL_GUI0_EDIT">
                    <Color id="51" val="1"/>
                  </PropertyList>
                </GuiDisplayTable>
                <GuiOutput id="160">
                  <PropertyList model="CTRL_GUI1_EDIT">
                    <Color id="51" val="1"/>
                  </PropertyList>
                </GuiOutput>
                <GuiOutputTable id="161">
                  <PropertyList model="CTRL_GUI1_EDIT">
                    <Color id="51" val="1"/>
                  </PropertyList>
                </GuiOutputTable>
                <NullValue id="167" val="0"/>
                <StoredAs id="173" val="1"/>
                <Definition id="175" val="2"/>
                <UpdateStyle id="176" val="A"/>
                <_Dec id="181"/>
                <_Whole id="182" val="8"/>
                <_Negative id="192"/>
              </PropertyList>
            </Column>
            <Column id="14" name="V)pszPort">
              <PropertyList model="FIELD">
                <Model attr_obj="FIELD_ALPHA" id="1"/>
                <Picture id="157" valUnicode="8"/>
                <GuiDisplay id="158">
                  <PropertyList model="CTRL_GUI0_EDIT">
                    <Color id="51" val="1"/>
                  </PropertyList>
                </GuiDisplay>
                <GuiDisplayTable id="159">
                  <PropertyList model="CTRL_GUI0_EDIT">
                    <Color id="51" val="1"/>
                  </PropertyList>
                </GuiDisplayTable>
                <GuiOutput id="160">
                  <PropertyList model="CTRL_GUI1_EDIT">
                    <Color id="51" val="1"/>
                  </PropertyList>
                </GuiOutput>
                <GuiOutputTable id="161">
                  <PropertyList model="CTRL_GUI1_EDIT">
                    <Color id="51" val="1"/>
                  </PropertyList>
                </GuiOutputTable>
                <NullValue id="167"/>
                <StoredAs id="173" val="1"/>
                <Size id="174" val="8"/>
                <Definition id="175" val="2"/>
                <_Flip id="194"/>
              </PropertyList>
            </Column>
            <Column id="15" name="V)lFirmCode">
              <PropertyList model="FIELD">
                <Model attr_obj="FIELD_NUMERIC" id="1"/>
                <Picture id="157" valUnicode="8"/>
                <GuiDisplay id="158">
                  <PropertyList model="CTRL_GUI0_EDIT">
                    <Color id="51" val="1"/>
                  </PropertyList>
                </GuiDisplay>
                <GuiDisplayTable id="159">
                  <PropertyList model="CTRL_GUI0_EDIT">
                    <Color id="51" val="1"/>
                  </PropertyList>
                </GuiDisplayTable>
                <GuiOutput id="160">
                  <PropertyList model="CTRL_GUI1_EDIT">
                    <Color id="51" val="1"/>
                  </PropertyList>
                </GuiOutput>
                <GuiOutputTable id="161">
                  <PropertyList model="CTRL_GUI1_EDIT">
                    <Color id="51" val="1"/>
                  </PropertyList>
                </GuiOutputTable>
                <NullValue id="167" val="0"/>
                <StoredAs id="173" val="1"/>
                <Definition id="175" val="2"/>
                <UpdateStyle id="176" val="A"/>
                <_Dec id="181"/>
                <_Whole id="182" val="8"/>
                <_Negative id="192"/>
              </PropertyList>
            </Column>
            <Column id="16" name="V)lUserCode">
              <PropertyList model="FIELD">
                <Model attr_obj="FIELD_NUMERIC" id="1"/>
                <Picture id="157" valUnicode="8"/>
                <GuiDisplay id="158">
                  <PropertyList model="CTRL_GUI0_EDIT">
                    <Color id="51" val="1"/>
                  </PropertyList>
                </GuiDisplay>
                <GuiDisplayTable id="159">
                  <PropertyList model="CTRL_GUI0_EDIT">
                    <Color id="51" val="1"/>
                  </PropertyList>
                </GuiDisplayTable>
                <GuiOutput id="160">
                  <PropertyList model="CTRL_GUI1_EDIT">
                    <Color id="51" val="1"/>
                  </PropertyList>
                </GuiOutput>
                <GuiOutputTable id="161">
                  <PropertyList model="CTRL_GUI1_EDIT">
                    <Color id="51" val="1"/>
                  </PropertyList>
                </GuiOutputTable>
                <NullValue id="167" val="0"/>
                <StoredAs id="173" val="1"/>
                <Definition id="175" val="2"/>
                <UpdateStyle id="176" val="A"/>
                <_Dec id="181"/>
                <_Whole id="182" val="8"/>
                <_Negative id="192"/>
              </PropertyList>
            </Column>
            <Column id="17" name="V)pvCtrl">
              <PropertyList model="FIELD">
                <Model attr_obj="FIELD_NUMERIC" id="1"/>
                <Picture id="157" valUnicode="8"/>
                <GuiDisplay id="158">
                  <PropertyList model="CTRL_GUI0_EDIT">
                    <Color id="51" val="1"/>
                  </PropertyList>
                </GuiDisplay>
                <GuiDisplayTable id="159">
                  <PropertyList model="CTRL_GUI0_EDIT">
                    <Color id="51" val="1"/>
                  </PropertyList>
                </GuiDisplayTable>
                <GuiOutput id="160">
                  <PropertyList model="CTRL_GUI1_EDIT">
                    <Color id="51" val="1"/>
                  </PropertyList>
                </GuiOutput>
                <GuiOutputTable id="161">
                  <PropertyList model="CTRL_GUI1_EDIT">
                    <Color id="51" val="1"/>
                  </PropertyList>
                </GuiOutputTable>
                <NullValue id="167" val="0"/>
                <StoredAs id="173" val="1"/>
                <Definition id="175" val="2"/>
                <UpdateStyle id="176" val="A"/>
                <_Dec id="181"/>
                <_Whole id="182" val="8"/>
                <_Negative id="192"/>
              </PropertyList>
            </Column>
            <Column id="18" name="V)戻り値">
              <PropertyList model="FIELD">
                <Model attr_obj="FIELD_NUMERIC" id="1"/>
                <Picture id="157" valUnicode="8"/>
                <GuiDisplay id="158">
                  <PropertyList model="CTRL_GUI0_EDIT">
                    <Color id="51" val="1"/>
                    <Border id="452" val="Y"/>
                  </PropertyList>
                </GuiDisplay>
                <GuiDisplayTable id="159">
                  <PropertyList model="CTRL_GUI0_EDIT">
                    <Color id="51" val="1"/>
                    <Border id="452" val="Y"/>
                  </PropertyList>
                </GuiDisplayTable>
                <GuiOutput id="160">
                  <PropertyList model="CTRL_GUI1_EDIT">
                    <Color id="51" val="1"/>
                  </PropertyList>
                </GuiOutput>
                <GuiOutputTable id="161">
                  <PropertyList model="CTRL_GUI1_EDIT">
                    <Color id="51" val="1"/>
                  </PropertyList>
                </GuiOutputTable>
                <NullValue id="167" val="0"/>
                <StoredAs id="173" val="1"/>
                <Definition id="175" val="2"/>
                <UpdateStyle id="176" val="A"/>
                <_Dec id="181"/>
                <_Whole id="182" val="8"/>
                <_Negative id="192"/>
              </PropertyList>
            </Column>
          </Columns>
          <ColumnsLastIsn val="18"/>
        </Resource>
        <Information>
          <Key>
            <Mode val="N"/>
          </Key>
          <DB comp="-1"/>
          <Sort>
            <CLS val="A"/>
          </Sort>
          <ForceRecordDelete DEL="N"/>
          <EndTaskCondition val="Y"/>
          <EvaluateEndCondition val="A"/>
          <InitialMode val="M"/>
          <Locate Direction="A"/>
          <Range Direction="A"/>
          <VarRange/>
          <TaskProperties>
            <SelectionTable val="N"/>
            <ConfirmUpdate CNFU="N"/>
            <ConfirmCancel val="N"/>
            <ErrorStrategy val="A"/>
            <LockingStrategy val="I"/>
            <CacheStrategy val="N"/>
            <ForceRecordSuffix val="Y"/>
            <TransactionMode val="P"/>
            <TransactionBegin val="N"/>
            <PreloadView val="N"/>
            <AllowEmptyDataview val="N"/>
            <KeepCreatedContext val="N"/>
          </TaskProperties>
          <SIDE_WIN>
            <AllowOptions val="N"/>
            <AllowQuery val="Y"/>
            <AllowModify val="Y"/>
            <AllowCreate val="Y"/>
            <AllowDelete val="Y"/>
            <AllowLocate val="Y"/>
            <AllowRange val="Y"/>
            <AllowIndexChange val="Y"/>
            <AllowSorting val="Y"/>
            <AllowIOFiles val="Y"/>
            <RecordCycle val="N"/>
            <AllowEvents val="Y"/>
            <AllowIndexOptimization val="Y"/>
            <AllowLocationInQuery val="Y"/>
            <AllowPrintingData val="N"/>
          </SIDE_WIN>
          <WIN>
            <OpenTaskWindow val="N"/>
            <CloseTaskWindow val="N"/>
            <ForegroundWindow val="N"/>
            <FlipFld val="N"/>
            <RefreshTaskWindow ReturnValue="N"/>
          </WIN>
          <BOX>
            <Direction val="V"/>
          </BOX>
        </Information>
        <INT_RECOMP_INFO>
          <v>9</v>
        </INT_RECOMP_INFO>
        <TaskLogic>
          <LogicUnit id="2" propagate="78">
            <Level val="R"/>
            <Type val="M"/>
            <_DspTemplate val="-1"/>
            <FieldID val="9"/>
            <_HeaderPosition val="1"/>
            <Scope val="S"/>
            <EngineDirective val="S"/>
            <ShowMessage val="Y"/>
            <Condition val="89"/>
            <_TotalVariabls val="9"/>
            <_TotalVirtuals val="9"/>
            <Event>
              <EventType val="S"/>
              <PublicObject comp="-1"/>
            </Event>
            <Expanded val="1"/>
            <LogicLines>
              <LogicLine>
                <DATAVIEW_SRC FlowIsn="2" Type="M">
                  <Condition val="N"/>
                  <Modifier val="B"/>
                  <Direction val="C"/>
                </DATAVIEW_SRC>
              </LogicLine>
              <LogicLine>
                <Select FieldID="1" FlowIsn="3" id="1">
                  <Column val="1"/>
                  <Type val="V"/>
                  <IsParameter val="N"/>
                  <_RecomputeLength val="1"/>
                  <_RecomputeIndex val="1"/>
                  <_FormIndex val="2"/>
                  <_ControlIndex val="2"/>
                  <_OleSubformIdx val="2"/>
                  <_TabbingOrderDspIndex val="2"/>
                  <DIFF_UPDATE val="T"/>
                  <Condition val="Y"/>
                  <Modifier val="S"/>
                  <Direction val="C"/>
                </Select>
              </LogicLine>
              <LogicLine>
                <Select FieldID="2" FlowIsn="4" id="2">
                  <Column val="2"/>
                  <Type val="V"/>
                  <IsParameter val="N"/>
                  <_RecomputeIndex val="1"/>
                  <_FormIndex val="1"/>
                  <_ControlIndex val="1"/>
                  <_OleSubformIdx val="1"/>
                  <_TabbingOrderDspIndex val="1"/>
                  <DIFF_UPDATE val="T"/>
                  <Condition val="Y"/>
                  <Modifier val="S"/>
                  <Direction val="C"/>
                </Select>
              </LogicLine>
              <LogicLine>
                <Remark FlowIsn="5">
                  <Type val="0"/>
                  <Text val=" "/>
                </Remark>
              </LogicLine>
              <LogicLine>
                <Select FieldID="3" FlowIsn="6" id="3">
                  <ASS val="7"/>
                  <Column val="3"/>
                  <Type val="V"/>
                  <IsParameter val="N"/>
                  <_RecomputeIndex val="1"/>
                  <_FormIndex val="1"/>
                  <_ControlIndex val="1"/>
                  <_OleSubformIdx val="1"/>
                  <_TabbingOrderDspIndex val="1"/>
                  <DIFF_UPDATE val="T"/>
                  <Condition val="Y"/>
                  <Modifier val="S"/>
                  <Direction val="C"/>
                </Select>
              </LogicLine>
              <LogicLine>
                <Select FieldID="4" FlowIsn="7" id="4">
                  <Column val="4"/>
                  <Type val="V"/>
                  <IsParameter val="N"/>
                  <_RecomputeIndex val="1"/>
                  <_FormIndex val="1"/>
                  <_ControlIndex val="1"/>
                  <_OleSubformIdx val="1"/>
                  <_TabbingOrderDspIndex val="1"/>
                  <DIFF_UPDATE val="T"/>
                  <Condition val="Y"/>
                  <Modifier val="S"/>
                  <Direction val="C"/>
                </Select>
              </LogicLine>
              <LogicLine>
                <Select FieldID="5" FlowIsn="8" id="5">
                  <ASS val="8"/>
                  <Column val="5"/>
                  <Type val="V"/>
                  <IsParameter val="N"/>
                  <_RecomputeIndex val="1"/>
                  <_FormIndex val="1"/>
                  <_ControlIndex val="1"/>
                  <_OleSubformIdx val="1"/>
                  <_TabbingOrderDspIndex val="1"/>
                  <DIFF_UPDATE val="T"/>
                  <Condition val="Y"/>
                  <Modifier val="S"/>
                  <Direction val="C"/>
                </Select>
              </LogicLine>
              <LogicLine>
                <Select FieldID="6" FlowIsn="9" id="6">
                  <ASS val="9"/>
                  <Column val="6"/>
                  <Type val="V"/>
                  <IsParameter val="N"/>
                  <_RecomputeIndex val="1"/>
                  <_FormIndex val="1"/>
                  <_ControlIndex val="1"/>
                  <_OleSubformIdx val="1"/>
                  <_TabbingOrderDspIndex val="1"/>
                  <DIFF_UPDATE val="T"/>
                  <Condition val="Y"/>
                  <Modifier val="S"/>
                  <Direction val="C"/>
                </Select>
              </LogicLine>
              <LogicLine>
                <Select FieldID="7" FlowIsn="10" id="7">
                  <ASS val="10"/>
                  <Column val="7"/>
                  <Type val="V"/>
                  <IsParameter val="N"/>
                  <_RecomputeIndex val="1"/>
                  <_FormIndex val="1"/>
                  <_ControlIndex val="1"/>
                  <_OleSubformIdx val="1"/>
                  <_TabbingOrderDspIndex val="1"/>
                  <DIFF_UPDATE val="T"/>
                  <Condition val="Y"/>
                  <Modifier val="S"/>
                  <Direction val="C"/>
                </Select>
              </LogicLine>
              <LogicLine>
                <Select FieldID="8" FlowIsn="11" id="8">
                  <Column val="8"/>
                  <Type val="V"/>
                  <IsParameter val="N"/>
                  <_RecomputeIndex val="1"/>
                  <_FormIndex val="1"/>
                  <_ControlIndex val="1"/>
                  <_OleSubformIdx val="1"/>
                  <_TabbingOrderDspIndex val="1"/>
                  <DIFF_UPDATE val="T"/>
                  <Condition val="Y"/>
                  <Modifier val="S"/>
                  <Direction val="C"/>
                </Select>
              </LogicLine>
              <LogicLine>
                <Remark FlowIsn="12">
                  <Type val="0"/>
                  <Text val=" "/>
                </Remark>
              </LogicLine>
              <LogicLine>
                <Select FieldID="9" FlowIsn="13" id="9">
                  <Column val="9"/>
                  <Type val="V"/>
                  <IsParameter val="N"/>
                  <_RecomputeIndex val="1"/>
                  <_FormIndex val="1"/>
                  <_ControlIndex val="1"/>
                  <_OleSubformIdx val="1"/>
                  <_TabbingOrderDspIndex val="1"/>
                  <DIFF_UPDATE val="T"/>
                  <Condition val="Y"/>
                  <Modifier val="S"/>
                  <Direction val="C"/>
                </Select>
              </LogicLine>
              <LogicLine>
                <Remark FlowIsn="14">
                  <Type val="0"/>
                  <Text val=" "/>
                </Remark>
              </LogicLine>
            </LogicLines>
          </LogicUnit>
          <LogicUnit id="3" propagate="78">
            <Level val="T"/>
            <Type val="P"/>
            <_DspTemplate val="-1"/>
            <_HeaderPosition val="1"/>
            <Scope val="S"/>
            <EngineDirective val="S"/>
            <ShowMessage val="Y"/>
            <Condition val="89"/>
            <Event>
              <EventType val="S"/>
              <PublicObject comp="-1"/>
            </Event>
            <Expanded val="1"/>
          </LogicUnit>
          <LogicUnit id="4" propagate="78">
            <Level val="T"/>
            <Type val="S"/>
            <_DspTemplate val="-1"/>
            <FieldID val="9"/>
            <_HeaderPosition val="1"/>
            <Scope val="S"/>
            <EngineDirective val="S"/>
            <ShowMessage val="Y"/>
            <Condition val="89"/>
            <Event>
              <EventType val="S"/>
              <PublicObject comp="-1"/>
            </Event>
            <Expanded val="1"/>
          </LogicUnit>
          <LogicUnit id="5" propagate="78">
            <Level val="R"/>
            <Type val="P"/>
            <_DspTemplate val="-1"/>
            <FieldID val="9"/>
            <_HeaderPosition val="1"/>
            <Scope val="S"/>
            <EngineDirective val="S"/>
            <ShowMessage val="Y"/>
            <Condition val="89"/>
            <Event>
              <EventType val="S"/>
              <PublicObject comp="-1"/>
            </Event>
            <Expanded val="1"/>
          </LogicUnit>
          <LogicUnit id="6" propagate="78">
            <Level val="R"/>
            <Type val="S"/>
            <_DspTemplate val="-1"/>
            <FieldID val="9"/>
            <_HeaderPosition val="1"/>
            <Scope val="S"/>
            <EngineDirective val="S"/>
            <ShowMessage val="Y"/>
            <Condition val="89"/>
            <Event>
              <EventType val="S"/>
              <PublicObject comp="-1"/>
            </Event>
            <Expanded val="1"/>
            <LogicLines>
              <LogicLine>
                <Update FlowIsn="15">
                  <FieldID val="9"/>
                  <WithValue val="1"/>
                  <Incremental val="N"/>
                  <ForcedUpdate val="Y"/>
                  <Condition val="Y"/>
                  <Modifier val="B"/>
                  <Direction val="C"/>
                </Update>
              </LogicLine>
              <LogicLine>
                <Evaluate FlowIsn="16">
                  <Expression val="11"/>
                  <Condition val="Y"/>
                  <Modifier val="B"/>
                  <Direction val="C"/>
                </Evaluate>
              </LogicLine>
              <LogicLine>
                <Remark FlowIsn="17">
                  <Type val="2"/>
                  <Text val=" "/>
                </Remark>
              </LogicLine>
              <LogicLine>
                <Remark FlowIsn="18">
                  <Type val="2"/>
                  <Text val="デモチェック"/>
                </Remark>
              </LogicLine>
              <LogicLine>
                <BLOCK EndBlock="24" EndBlockSegment="24" FlowIsn="19" Type="I">
                  <Condition Exp="4"/>
                  <Modifier val="B"/>
                  <Direction val="C"/>
                </BLOCK>
              </LogicLine>
              <LogicLine>
                <Update FlowIsn="20">
                  <FieldID val="9"/>
                  <WithValue val="2"/>
                  <Incremental val="N"/>
                  <ForcedUpdate val="Y"/>
                  <Condition val="Y"/>
                  <Modifier val="B"/>
                  <Direction val="C"/>
                </Update>
              </LogicLine>
              <LogicLine>
                <Evaluate FlowIsn="21">
                  <Expression val="11"/>
                  <Condition val="Y"/>
                  <Modifier val="B"/>
                  <Direction val="C"/>
                </Evaluate>
              </LogicLine>
              <LogicLine>
                <BLOCK EndBlock="23" EndBlockSegment="23" FlowIsn="22" Type="I">
                  <Condition Exp="5"/>
                  <Modifier val="B"/>
                  <Direction val="C"/>
                </BLOCK>
              </LogicLine>
              <LogicLine>
                <Update FlowIsn="23">
                  <FieldID val="2"/>
                  <WithValue val="6"/>
                  <Incremental val="N"/>
                  <ForcedUpdate val="Y"/>
                  <Condition val="Y"/>
                  <Modifier val="B"/>
                  <Direction val="C"/>
                </Update>
              </LogicLine>
              <LogicLine>
                <END_BLK FlowIsn="24"/>
              </LogicLine>
              <LogicLine>
                <END_BLK FlowIsn="25"/>
              </LogicLine>
              <LogicLine>
                <STP Buttons="O" DefaultButton="1" ERR_LOG_DEF_CHG="N" Exp="12" FlowIsn="26" IMG_DEF_CHG="N" Image="E" Mode="W" TTL_DEF_CHG="N" TitleTxt="警告" VR_DISP="B">
                  <AppendToErrorLog val="N"/>
                  <Condition val="N"/>
                  <Modifier val="B"/>
                  <Direction val="C"/>
                </STP>
              </LogicLine>
              <LogicLine>
                <Remark FlowIsn="27">
                  <Type val="2"/>
                  <Text val=" "/>
                </Remark>
              </LogicLine>
              <LogicLine>
                <BLOCK EndBlock="30" EndBlockSegment="30" FlowIsn="28" Type="I">
                  <Condition Exp="4"/>
                  <Modifier val="B"/>
                  <Direction val="C"/>
                </BLOCK>
              </LogicLine>
              <LogicLine>
                <STP Buttons="O" DefaultButton="1" ERR_LOG_DEF_CHG="N" FlowIsn="29" IMG_DEF_CHG="N" Image="E" Mode="W" TTL_DEF_CHG="N" TXT="ライセンスエラー" TitleTxt="警告" VR_DISP="B">
                  <AppendToErrorLog val="N"/>
                  <Condition val="Y"/>
                  <Modifier val="B"/>
                  <Direction val="C"/>
                </STP>
              </LogicLine>
              <LogicLine>
                <Evaluate FlowIsn="30">
                  <Expression val="3"/>
                  <Condition val="Y"/>
                  <Modifier val="B"/>
                  <Direction val="C"/>
                </Evaluate>
              </LogicLine>
              <LogicLine>
                <END_BLK FlowIsn="31"/>
              </LogicLine>
              <LogicLine>
                <Remark FlowIsn="32">
                  <Type val="2"/>
                  <Text val=" "/>
                </Remark>
              </LogicLine>
            </LogicLines>
          </LogicUnit>
        </TaskLogic>
        <TaskForms>
          <FormEntry id="2">
            <PropertyList model="FORM_GUI0">
              <Color id="51" val="1"/>
              <_Comment id="218"/>
              <FormName id="311" valUnicode="ﾌﾟﾛﾃｸﾄﾁｪｯｸ(売上)"/>
              <_TabbingOrder id="318" val="1"/>
              <WindowType id="358" val="1"/>
              <PersistentFormState id="493"/>
            </PropertyList>
          </FormEntry>
        </TaskForms>
        <Expressions>
          <Expression id="1">
            <ExpSyntax val="CallDLL ('wkwin32.WkbOpen2','44A4444',{0,3},{0,4},{0,5},{0,6},{0,7},{0,8})"/>
            <ExpAttribute val="*"/>
          </Expression>
          <Expression id="2">
            <ExpSyntax val="CallDLL ('wkwin32.WkbOpen2','44A4444',{0,3},{0,4},{0,5},{0,6},10,{0,8})"/>
            <ExpAttribute val="*"/>
          </Expression>
          <Expression id="3">
            <ExpSyntax val="KbPut ('Close Application'EVENT)"/>
            <ExpAttribute val="B"/>
          </Expression>
          <Expression id="4">
            <ExpSyntax val="{0,9}=0"/>
            <ExpAttribute val="B"/>
          </Expression>
          <Expression id="5">
            <ExpSyntax val="{0,9}>0"/>
            <ExpAttribute val="B"/>
          </Expression>
          <Expression id="6">
            <ExpSyntax val="1"/>
            <ExpAttribute val="N"/>
          </Expression>
          <Expression id="7">
            <ExpSyntax val="1"/>
            <ExpAttribute val="N"/>
          </Expression>
          <Expression id="8">
            <ExpSyntax val="'*'"/>
            <ExpAttribute val="A"/>
          </Expression>
          <Expression id="9">
            <ExpSyntax val="2258"/>
            <ExpAttribute val="N"/>
          </Expression>
          <Expression id="10">
            <ExpSyntax val="{0,1}"/>
            <ExpAttribute val="N"/>
          </Expression>
          <Expression id="11">
            <ExpSyntax val="CallDLL ('wkwin32.WkbClose','44',{0,9})"/>
            <ExpAttribute val="*"/>
          </Expression>
          <Expression id="12">
            <ExpSyntax val="'$'&amp;Str ({0,9},'2')"/>
            <ExpAttribute val="A"/>
          </Expression>
        </Expressions>
      </Task>
    </Programs>
  </ProgramsRepository>

</Application>
